{"cameraMode":{"drawMode":0,"name":"Shaded","section":"Shading Mode"},"sceneLighting":false,"audioPlay":false,"sceneViewState":{"m_AlwaysRefresh":false,"showFog":true,"showSkybox":false,"showFlares":true,"showImageEffects":true,"showParticleSystems":true,"showVisualEffectGraphs":true,"m_FxEnabled":false},"in2DMode":false,"pivot":{"x":0.10087060928344727,"y":2.4756033420562746,"z":-0.12090587615966797},"rotation":{"x":-0.06837578117847443,"y":0.8149356245994568,"z":-0.0982637107372284,"w":-0.56705641746521},"size":3.486729621887207,"orthographic":false}